Workbook

Sheet Summary
A1: Telco churn: summary
A2: Real data: IBM Telco Customer Churn sample. Every value is a formula over the other sheets.
A4: KPI | B4: Value
A5: Customers | B5: =Segments!C5+Segments!C6+Segments!C7 -> 7043
A6: Churned customers | B6: =Segments!D5+Segments!D6+Segments!D7 -> 1869
A7: Churn rate | B7: =B6/B5 -> 0.26536987
A8: Monthly revenue lost to churn ($) | B8: =Segments!E5+Segments!E6+Segments!E7 -> 139130.85
A9: Annualised revenue lost ($) | B9: =B8*12 -> 1669570.2
A10: Recommended campaign: customers targeted | B10: ='ROI Calculator'!B13 -> 2356
A11: Recommended campaign: net value ($) | B11: ='ROI Calculator'!B22 -> 142791.46
A12: Recommended campaign: ROI | B12: ='ROI Calculator'!B23 -> 0.61828515
A13: Recommended campaign: break-even save rate | B13: ='ROI Calculator'!B24 -> 0.18538142
A14: High-risk band: expected MRR at risk ($) | B14: ='Risk bands'!F5 -> 81604.37
A16: Campaign rows reflect the ROI Calculator as saved (model group, default assumptions).

Sheet ROI Calculator
A1: Retention campaign ROI calculator
A2: Yellow cells are inputs. Pick a target group in B5; every result is a formula.
A4: Inputs
A5: Target group | B5: Model: churn probability >= threshold
A6: Discount on monthly bill | B6: 0.2
A7: Discount length (months) | B7: 6
A8: Contact cost per targeted customer ($) | B8: 5
A9: Save rate: share of would-be churners retained | B9: 0.3
A10: Revenue horizon for a saved customer (months) | B10: 12
A12: Selected group
A13: Customers targeted | B13: =INDEX(Groups!B$5:B$8,MATCH($B$5,Groups!$A$5:$A$8,0)) -> 2356
A14: Would-be churners in group | B14: =INDEX(Groups!C$5:C$8,MATCH($B$5,Groups!$A$5:$A$8,0)) -> 1325
A15: Churner MRR ($) | B15: =INDEX(Groups!E$5:E$8,MATCH($B$5,Groups!$A$5:$A$8,0)) -> 103816.4
A16: Group MRR ($) | B16: =INDEX(Groups!F$5:F$8,MATCH($B$5,Groups!$A$5:$A$8,0)) -> 182639.65
A18: Results
A19: Customers saved | B19: =B14*B9 -> 397.5
A20: Revenue saved over horizon ($) | B20: =B9*B15*B10 -> 373739.04
A21: Campaign cost: contact + discount ($) | B21: =B8*B13+B6*B7*B16 -> 230947.58
A22: Net value ($) | B22: =B20-B21 -> 142791.46
A23: ROI (net / cost) | B23: =IF(B21=0,0,B22/B21) -> 0.61828515
A24: Break-even save rate | B24: =IF(B15=0,"n/a",B21/(B15*B10)) -> 0.18538142
A25: Cost per customer saved ($) | B25: =IF(B19=0,"n/a",B21/B19) -> 581.0002
A28: Sensitivity: net value ($) by save rate and discount, selected group
A29: Save rate \ discount | B29: 10% | C29: 15% | D29: 20% | E29: 25% | F29: 30%
A30: discount -> | B30: 0.1 | C30: 0.15 | D30: 0.2 | E30: 0.25 | F30: 0.3
A31: 0.1 | B31: =$A31*$B$15*$B$10-($B$8*$B$13+B$30*$B$7*$B$16) -> 3215.89 | C31: =$A31*$B$15*$B$10-($B$8*$B$13+C$30*$B$7*$B$16) -> -51576.005 | D31: =$A31*$B$15*$B$10-($B$8*$B$13+D$30*$B$7*$B$16) -> -106367.9 | E31: =$A31*$B$15*$B$10-($B$8*$B$13+E$30*$B$7*$B$16) -> -161159.79 | F31: =$A31*$B$15*$B$10-($B$8*$B$13+F$30*$B$7*$B$16) -> -215951.69
A32: 0.2 | B32: =$A32*$B$15*$B$10-($B$8*$B$13+B$30*$B$7*$B$16) -> 127795.57 | C32: =$A32*$B$15*$B$10-($B$8*$B$13+C$30*$B$7*$B$16) -> 73003.675 | D32: =$A32*$B$15*$B$10-($B$8*$B$13+D$30*$B$7*$B$16) -> 18211.78 | E32: =$A32*$B$15*$B$10-($B$8*$B$13+E$30*$B$7*$B$16) -> -36580.115 | F32: =$A32*$B$15*$B$10-($B$8*$B$13+F$30*$B$7*$B$16) -> -91372.01
A33: 0.3 | B33: =$A33*$B$15*$B$10-($B$8*$B$13+B$30*$B$7*$B$16) -> 252375.25 | C33: =$A33*$B$15*$B$10-($B$8*$B$13+C$30*$B$7*$B$16) -> 197583.36 | D33: =$A33*$B$15*$B$10-($B$8*$B$13+D$30*$B$7*$B$16) -> 142791.46 | E33: =$A33*$B$15*$B$10-($B$8*$B$13+E$30*$B$7*$B$16) -> 87999.565 | F33: =$A33*$B$15*$B$10-($B$8*$B$13+F$30*$B$7*$B$16) -> 33207.67
A34: 0.4 | B34: =$A34*$B$15*$B$10-($B$8*$B$13+B$30*$B$7*$B$16) -> 376954.93 | C34: =$A34*$B$15*$B$10-($B$8*$B$13+C$30*$B$7*$B$16) -> 322163.04 | D34: =$A34*$B$15*$B$10-($B$8*$B$13+D$30*$B$7*$B$16) -> 267371.14 | E34: =$A34*$B$15*$B$10-($B$8*$B$13+E$30*$B$7*$B$16) -> 212579.24 | F34: =$A34*$B$15*$B$10-($B$8*$B$13+F$30*$B$7*$B$16) -> 157787.35
A35: 0.5 | B35: =$A35*$B$15*$B$10-($B$8*$B$13+B$30*$B$7*$B$16) -> 501534.61 | C35: =$A35*$B$15*$B$10-($B$8*$B$13+C$30*$B$7*$B$16) -> 446742.71 | D35: =$A35*$B$15*$B$10-($B$8*$B$13+D$30*$B$7*$B$16) -> 391950.82 | E35: =$A35*$B$15*$B$10-($B$8*$B$13+E$30*$B$7*$B$16) -> 337158.92 | F35: =$A35*$B$15*$B$10-($B$8*$B$13+F$30*$B$7*$B$16) -> 282367.03

Sheet Groups
A1: Candidate target groups
A2: Values from the out-of-fold model scores (src/model.py). Churn rate is a formula.
A4: Group | B4: Customers | C4: Churners | D4: Churn rate | E4: Churner MRR ($) | F4: Group MRR ($)
A5: Model: churn probability >= threshold | B5: 2356 | C5: 1325 | D5: =C5/B5 -> 0.56239389 | E5: 103816.4 | F5: 182639.65
A6: Rule: month-to-month + fiber + first year | B6: 916 | C6: 643 | D6: =C6/B6 -> 0.70196507 | E6: 53178.3 | F6: 75183.15
A7: All month-to-month customers | B7: 3875 | C7: 1655 | D7: =C7/B7 -> 0.42709677 | E7: 120847.1 | F7: 257294.15
A8: Everyone | B8: 7043 | C8: 1869 | D8: =C8/B8 -> 0.26536987 | E8: 139130.85 | F8: 456116.6
A10: Model threshold used: 0.35 (chosen by maximum net value on training folds)

Sheet Segments
A1: Churn by segment with Wilson 95% confidence intervals
A2: Values: customers, churned, MRR lost. Rate, CI and shares are formulas; z in B3.
A3: z (95%) | B3: =_xludf.NORM.S.INV(0.975) -> #NAME?
A4: Dimension | B4: Segment | C4: Customers | D4: Churned | E4: MRR lost ($) | F4: Churn rate | G4: CI low | H4: CI high | I4: Share of MRR lost
A5: contract | B5: Month-to-month | C5: 3875 | D5: 1655 | E5: 120847.1 | F5: =D5/C5 -> 0.42709677 | G5: =(F5+$B$3^2/(2*C5)-$B$3*SQRT(F5*(1-F5)/C5+$B$3^2/(4*C5^2)))/(1+$B$3^2/C5) -> #NAME? | H5: =(F5+$B$3^2/(2*C5)+$B$3*SQRT(F5*(1-F5)/C5+$B$3^2/(4*C5^2)))/(1+$B$3^2/C5) -> #NAME? | I5: =E5/SUMIF($A$5:$A$55,A5,$E$5:$E$55) -> 0.86858594
A6: contract | B6: One year | C6: 1473 | D6: 166 | E6: 14118.45 | F6: =D6/C6 -> 0.11269518 | G6: =(F6+$B$3^2/(2*C6)-$B$3*SQRT(F6*(1-F6)/C6+$B$3^2/(4*C6^2)))/(1+$B$3^2/C6) -> #NAME? | H6: =(F6+$B$3^2/(2*C6)+$B$3*SQRT(F6*(1-F6)/C6+$B$3^2/(4*C6^2)))/(1+$B$3^2/C6) -> #NAME? | I6: =E6/SUMIF($A$5:$A$55,A6,$E$5:$E$55) -> 0.10147606
A7: contract | B7: Two year | C7: 1695 | D7: 48 | E7: 4165.3 | F7: =D7/C7 -> 0.028318584 | G7: =(F7+$B$3^2/(2*C7)-$B$3*SQRT(F7*(1-F7)/C7+$B$3^2/(4*C7^2)))/(1+$B$3^2/C7) -> #NAME? | H7: =(F7+$B$3^2/(2*C7)+$B$3*SQRT(F7*(1-F7)/C7+$B$3^2/(4*C7^2)))/(1+$B$3^2/C7) -> #NAME? | I7: =E7/SUMIF($A$5:$A$55,A7,$E$5:$E$55) -> 0.029938004
A8: tenure_band | B8: 00-12 months | C8: 2186 | D8: 1037 | E8: 68954.25 | F8: =D8/C8 -> 0.47438243 | G8: =(F8+$B$3^2/(2*C8)-$B$3*SQRT(F8*(1-F8)/C8+$B$3^2/(4*C8^2)))/(1+$B$3^2/C8) -> #NAME? | H8: =(F8+$B$3^2/(2*C8)+$B$3*SQRT(F8*(1-F8)/C8+$B$3^2/(4*C8^2)))/(1+$B$3^2/C8) -> #NAME? | I8: =E8/SUMIF($A$5:$A$55,A8,$E$5:$E$55) -> 0.49560719
A9: tenure_band | B9: 13-24 months | C9: 1024 | D9: 294 | E9: 23081.65 | F9: =D9/C9 -> 0.28710938 | G9: =(F9+$B$3^2/(2*C9)-$B$3*SQRT(F9*(1-F9)/C9+$B$3^2/(4*C9^2)))/(1+$B$3^2/C9) -> #NAME? | H9: =(F9+$B$3^2/(2*C9)+$B$3*SQRT(F9*(1-F9)/C9+$B$3^2/(4*C9^2)))/(1+$B$3^2/C9) -> #NAME? | I9: =E9/SUMIF($A$5:$A$55,A9,$E$5:$E$55) -> 0.16589886
A10: tenure_band | B10: 25-48 months | C10: 1594 | D10: 325 | E10: 27462.5 | F10: =D10/C10 -> 0.20388959 | G10: =(F10+$B$3^2/(2*C10)-$B$3*SQRT(F10*(1-F10)/C10+$B$3^2/(4*C10^2)))/(1+$B$3^2/C10) -> #NAME? | H10: =(F10+$B$3^2/(2*C10)+$B$3*SQRT(F10*(1-F10)/C10+$B$3^2/(4*C10^2)))/(1+$B$3^2/C10) -> #NAME? | I10: =E10/SUMIF($A$5:$A$55,A10,$E$5:$E$55) -> 0.19738613
A11: tenure_band | B11: 49-72 months | C11: 2239 | D11: 213 | E11: 19632.45 | F11: =D11/C11 -> 0.095131755 | G11: =(F11+$B$3^2/(2*C11)-$B$3*SQRT(F11*(1-F11)/C11+$B$3^2/(4*C11^2)))/(1+$B$3^2/C11) -> #NAME? | H11: =(F11+$B$3^2/(2*C11)+$B$3*SQRT(F11*(1-F11)/C11+$B$3^2/(4*C11^2)))/(1+$B$3^2/C11) -> #NAME? | I11: =E11/SUMIF($A$5:$A$55,A11,$E$5:$E$55) -> 0.14110781
A12: internet_service | B12: DSL | C12: 2421 | D12: 459 | E12: 22529.2 | F12: =D12/C12 -> 0.18959108 | G12: =(F12+$B$3^2/(2*C12)-$B$3*SQRT(F12*(1-F12)/C12+$B$3^2/(4*C12^2)))/(1+$B$3^2/C12) -> #NAME? | H12: =(F12+$B$3^2/(2*C12)+$B$3*SQRT(F12*(1-F12)/C12+$B$3^2/(4*C12^2)))/(1+$B$3^2/C12) -> #NAME? | I12: =E12/SUMIF($A$5:$A$55,A12,$E$5:$E$55) -> 0.16192814
A13: internet_service | B13: Fiber optic | C13: 3096 | D13: 1297 | E13: 114300.05 | F13: =D13/C13 -> 0.41892765 | G13: =(F13+$B$3^2/(2*C13)-$B$3*SQRT(F13*(1-F13)/C13+$B$3^2/(4*C13^2)))/(1+$B$3^2/C13) -> #NAME? | H13: =(F13+$B$3^2/(2*C13)+$B$3*SQRT(F13*(1-F13)/C13+$B$3^2/(4*C13^2)))/(1+$B$3^2/C13) -> #NAME? | I13: =E13/SUMIF($A$5:$A$55,A13,$E$5:$E$55) -> 0.82152916
A14: internet_service | B14: No | C14: 1526 | D14: 113 | E14: 2301.6 | F14: =D14/C14 -> 0.074049803 | G14: =(F14+$B$3^2/(2*C14)-$B$3*SQRT(F14*(1-F14)/C14+$B$3^2/(4*C14^2)))/(1+$B$3^2/C14) -> #NAME? | H14: =(F14+$B$3^2/(2*C14)+$B$3*SQRT(F14*(1-F14)/C14+$B$3^2/(4*C14^2)))/(1+$B$3^2/C14) -> #NAME? | I14: =E14/SUMIF($A$5:$A$55,A14,$E$5:$E$55) -> 0.016542701
A15: payment_method | B15: Bank transfer (automatic) | C15: 1544 | D15: 258 | E15: 20091.9 | F15: =D15/C15 -> 0.16709845 | G15: =(F15+$B$3^2/(2*C15)-$B$3*SQRT(F15*(1-F15)/C15+$B$3^2/(4*C15^2)))/(1+$B$3^2/C15) -> #NAME? | H15: =(F15+$B$3^2/(2*C15)+$B$3*SQRT(F15*(1-F15)/C15+$B$3^2/(4*C15^2)))/(1+$B$3^2/C15) -> #NAME? | I15: =E15/SUMIF($A$5:$A$55,A15,$E$5:$E$55) -> 0.1444101
A16: payment_method | B16: Credit card (automatic) | C16: 1522 | D16: 232 | E16: 17946.6 | F16: =D16/C16 -> 0.15243101 | G16: =(F16+$B$3^2/(2*C16)-$B$3*SQRT(F16*(1-F16)/C16+$B$3^2/(4*C16^2)))/(1+$B$3^2/C16) -> #NAME? | H16: =(F16+$B$3^2/(2*C16)+$B$3*SQRT(F16*(1-F16)/C16+$B$3^2/(4*C16^2)))/(1+$B$3^2/C16) -> #NAME? | I16: =E16/SUMIF($A$5:$A$55,A16,$E$5:$E$55) -> 0.1289908
... A55: gender | B55: Male | C55: 3555 | D55: 930 | E55: 68882.3 | F55: =D55/C55 -> 0.26160338 | G55: =(F55+$B$3^2/(2*C55)-$B$3*SQRT(F55*(1-F55)/C55+$B$3^2/(4*C55^2)))/(1+$B$3^2/C55) -> #NAME? | H55: =(F55+$B$3^2/(2*C55)+$B$3*SQRT(F55*(1-F55)/C55+$B$3^2/(4*C55^2)))/(1+$B$3^2/C55) -> #NAME? | I55: =E55/SUMIF($A$5:$A$55,A55,$E$5:$E$55) -> 0.49509005

Sheet Risk bands
A1: Model risk bands (out-of-fold scores)
A2: High >= 50% predicted churn, Medium 25-50%, Low < 25%. Shares are formulas.
A4: Risk band | B4: Customers | C4: Actual churn rate | D4: Avg predicted probability | E4: MRR ($) | F4: Expected MRR at risk ($) | G4: Share of customers | H4: Share of expected risk
A5: 1. High | B5: 1569 | C5: 0.658381 | D5: 0.644298 | E5: 126069.25 | F5: 81604.37 | G5: =B5/SUM($B$5:$B$7) -> 0.22277439 | H5: =F5/SUM($F$5:$F$7) -> 0.58578267
A6: 2. Medium | B6: 1451 | C6: 0.341833 | D6: 0.366959 | E6: 102017.7 | F6: 37648.23 | G6: =B6/SUM($B$5:$B$7) -> 0.20602016 | H6: =F6/SUM($F$5:$F$7) -> 0.27025122
A7: 3. Low | B7: 4023 | C7: 0.084514 | D7: 0.081526 | E7: 228029.65 | F7: 20055.67 | G7: =B7/SUM($B$5:$B$7) -> 0.57120545 | H7: =F7/SUM($F$5:$F$7) -> 0.14396611

Sheet Lift
A1: Lift and cumulative gains by risk decile (test set)
A2: Values: customers and churners per decile. Rate, lift and capture are formulas.
A4: Decile | B4: Customers | C4: Churners | D4: Churn rate | E4: Lift | F4: Cumulative share of churners
A5: 1 | B5: 177 | C5: 131 | D5: =C5/B5 -> 0.74011299 | E5: =D5/(SUM($C$5:$C$14)/SUM($B$5:$B$14)) -> 2.7908758 | F5: =SUM($C$5:C5)/SUM($C$5:$C$14) -> 0.28051392
A6: 2 | B6: 177 | C6: 105 | D6: =C6/B6 -> 0.59322034 | E6: =D6/(SUM($C$5:$C$14)/SUM($B$5:$B$14)) -> 2.2369615 | F6: =SUM($C$5:C6)/SUM($C$5:$C$14) -> 0.50535332
A7: 3 | B7: 177 | C7: 75 | D7: =C7/B7 -> 0.42372881 | E7: =D7/(SUM($C$5:$C$14)/SUM($B$5:$B$14)) -> 1.5978296 | F7: =SUM($C$5:C7)/SUM($C$5:$C$14) -> 0.66595289
A8: 4 | B8: 177 | C8: 59 | D8: =C8/B8 -> 0.33333333 | E8: =D8/(SUM($C$5:$C$14)/SUM($B$5:$B$14)) -> 1.2569593 | F8: =SUM($C$5:C8)/SUM($C$5:$C$14) -> 0.79229122
A9: 5 | B9: 177 | C9: 41 | D9: =C9/B9 -> 0.23163842 | E9: =D9/(SUM($C$5:$C$14)/SUM($B$5:$B$14)) -> 0.8734802 | F9: =SUM($C$5:C9)/SUM($C$5:$C$14) -> 0.88008565
A10: 6 | B10: 177 | C10: 25 | D10: =C10/B10 -> 0.14124294 | E10: =D10/(SUM($C$5:$C$14)/SUM($B$5:$B$14)) -> 0.53260988 | F10: =SUM($C$5:C10)/SUM($C$5:$C$14) -> 0.93361884
A11: 7 | B11: 177 | C11: 22 | D11: =C11/B11 -> 0.12429379 | E11: =D11/(SUM($C$5:$C$14)/SUM($B$5:$B$14)) -> 0.46869669 | F11: =SUM($C$5:C11)/SUM($C$5:$C$14) -> 0.98072805
A12: 8 | B12: 177 | C12: 5 | D12: =C12/B12 -> 0.028248588 | E12: =D12/(SUM($C$5:$C$14)/SUM($B$5:$B$14)) -> 0.10652198 | F12: =SUM($C$5:C12)/SUM($C$5:$C$14) -> 0.99143469
A13: 9 | B13: 177 | C13: 3 | D13: =C13/B13 -> 0.016949153 | E13: =D13/(SUM($C$5:$C$14)/SUM($B$5:$B$14)) -> 0.063913185 | F13: =SUM($C$5:C13)/SUM($C$5:$C$14) -> 0.99785867
A14: 10 | B14: 168 | C14: 1 | D14: =C14/B14 -> 0.005952381 | E14: =D14/(SUM($C$5:$C$14)/SUM($B$5:$B$14)) -> 0.022445702 | F14: =SUM($C$5:C14)/SUM($C$5:$C$14) -> 1
